README.md
setup.py
BLECommandlineTool/__init__.py
BLECommandlineTool/blemap.py
BLECommandlineTool/parser_config.py
BLECommandlineTool.egg-info/PKG-INFO
BLECommandlineTool.egg-info/SOURCES.txt
BLECommandlineTool.egg-info/dependency_links.txt
BLECommandlineTool.egg-info/requires.txt
BLECommandlineTool.egg-info/top_level.txt
BLECommandlineTool/a_files/__init__.py
BLECommandlineTool/api/BLEBackendServices.py
BLECommandlineTool/api/__init__.py
BLECommandlineTool/b_files/__init__.py
BLECommandlineTool/common/__init__.py
BLECommandlineTool/common/utils.py
BLECommandlineTool/working_dir/__init__.py