Metadata-Version: 2.1
Name: BLECommandlineTool
Version: 0.0.3
Summary: commandlinetool and api for blemap backend services.
Home-page: https://github.com/occy88/BLECommandlineTool
Author: octavio
Author-email: octavio.delser@gmail.com
License: UNKNOWN
Platform: UNKNOWN
Classifier: Programming Language :: Python :: 3
Classifier: License :: OSI Approved :: MIT License
Classifier: Operating System :: OS Independent
Requires-Python: >=3.6
